{
"skeleton": { "hash": "+tA0Fe9jkVGzOBxIr2bBZy79a/g", "spine": "2.1.27", "width": 734, "height": 1355, "images": "./images/" },
"bones": [
	{ "name": "root" },
	{ "name": "body", "parent": "root", "x": 799.57, "y": 315.44 },
	{ "name": "arms", "parent": "body", "x": -17.39, "y": 528.05 },
	{ "name": "head", "parent": "body", "x": -33.2, "y": 652.95 },
	{ "name": "brows", "parent": "head", "x": -1.58, "y": 205.53 },
	{ "name": "hari", "parent": "head", "x": -4.74, "y": 129.64 }
],
"slots": [
	{ "name": "backsleeve", "bone": "arms", "attachment": "backsleeve" },
	{ "name": "mid", "bone": "body", "attachment": "mid" },
	{ "name": "frontarmbits", "bone": "arms", "attachment": "frontarmbits" },
	{ "name": "armskin", "bone": "arms", "attachment": "armskin" },
	{ "name": "backhairbase", "bone": "hari", "attachment": "backhairbase" },
	{ "name": "facebase", "bone": "head", "attachment": "facebase" },
	{ "name": "eyebrows", "bone": "brows", "attachment": "eyebrows" }
],
"skins": {
	"default": {
		"armskin": {
			"armskin": { "x": 14.32, "y": -596, "width": 415, "height": 383 }
		},
		"backhairbase": {
			"backhairbase": { "x": -38.62, "y": 3.95, "width": 734, "height": 404 }
		},
		"backsleeve": {
			"backsleeve": { "x": 173.82, "y": -238.5, "width": 156, "height": 556 }
		},
		"eyebrows": {
			"eyebrows": { "x": -8.78, "y": -5.93, "width": 144, "height": 44 }
		},
		"facebase": {
			"facebase": { "x": -44.86, "y": 171.09, "width": 429, "height": 431 }
		},
		"frontarmbits": {
			"frontarmbits": { "x": -127.67, "y": -214, "width": 221, "height": 615 }
		},
		"mid": {
			"mid": { "x": -40.57, "y": 175.05, "width": 428, "height": 981 }
		}
	}
},
"animations": {
	"idle": {
		"bones": {
			"body": {
				"translate": [
					{
						"time": 0,
						"x": 0,
						"y": 0,
						"curve": [ 0.25, 0, 0.75, 1 ]
					},
					{
						"time": 1,
						"x": 0,
						"y": -18.52,
						"curve": [ 0.25, 0, 0.75, 1 ]
					},
					{ "time": 2, "x": 0, "y": 0 }
				]
			},
			"arms": {
				"rotate": [
					{
						"time": 0,
						"angle": 0.66,
						"curve": [ 0.25, 0, 0.75, 1 ]
					},
					{
						"time": 0.3333,
						"angle": 0,
						"curve": [ 0.25, 0, 0.75, 1 ]
					},
					{
						"time": 1.3333,
						"angle": 2,
						"curve": [ 0.25, 0, 0.75, 1 ]
					},
					{ "time": 2, "angle": 0.66 }
				]
			},
			"head": {
				"rotate": [
					{
						"time": 0,
						"angle": -1.4,
						"curve": [ 0.25, 0, 0.75, 1 ]
					},
					{
						"time": 0.3333,
						"angle": 0,
						"curve": [ 0.25, 0, 0.75, 1 ]
					},
					{
						"time": 1.3333,
						"angle": -4.2,
						"curve": [ 0.25, 0, 0.75, 1 ]
					},
					{ "time": 2, "angle": -1.4 }
				]
			}
		}
	},
	"start": {
		"bones": {
			"body": {
				"translate": [
					{
						"time": 0,
						"x": 0,
						"y": 0,
						"curve": [ 0.25, 0, 0.75, 1 ]
					},
					{
						"time": 0.1666,
						"x": 0,
						"y": -30.1,
						"curve": [ 0.25, 0, 0.75, 1 ]
					},
					{ "time": 1, "x": 0, "y": 0 }
				]
			},
			"arms": {
				"translate": [
					{
						"time": 0,
						"x": 0,
						"y": 0,
						"curve": [ 0.25, 0, 0.75, 1 ]
					},
					{
						"time": 0.1666,
						"x": 0,
						"y": 6.94,
						"curve": [ 0.25, 0, 0.75, 1 ]
					},
					{
						"time": 0.6666,
						"x": 0,
						"y": 23.16,
						"curve": [ 0.25, 0, 0.75, 1 ]
					},
					{ "time": 1, "x": 0, "y": 0 }
				]
			},
			"hari": {
				"translate": [
					{
						"time": 0,
						"x": 0,
						"y": 0,
						"curve": [ 0.25, 0, 0.75, 1 ]
					},
					{
						"time": 0.1666,
						"x": 0,
						"y": 25.47,
						"curve": [ 0.25, 0, 0.75, 1 ]
					},
					{ "time": 1, "x": 0, "y": 0 }
				],
				"scale": [
					{
						"time": 0,
						"x": 1,
						"y": 1,
						"curve": [ 0.25, 0, 0.75, 1 ]
					},
					{
						"time": 0.1666,
						"x": 1,
						"y": 0.837,
						"curve": [ 0.25, 0, 0.75, 1 ]
					},
					{ "time": 1, "x": 1, "y": 1 }
				]
			}
		}
	}
}
}