{
"skeleton": { "hash": "H22PqxGa/gH+IDyi6qlOvxjjOfc", "spine": "2.1.27", "width": 745, "height": 1115, "images": "./images/" },
"bones": [
	{ "name": "root" },
	{ "name": "body", "parent": "root", "x": 768.55, "y": 158.09 },
	{ "name": "head", "parent": "body", "x": 42.93, "y": 585.44 },
	{ "name": "brow", "parent": "head", "x": -75.45, "y": 184.74 },
	{ "name": "tears", "parent": "head", "x": -78.06, "y": 150.91 }
],
"slots": [
	{ "name": "body", "bone": "body", "attachment": "body" },
	{ "name": "face", "bone": "head", "attachment": "face" },
	{ "name": "tears", "bone": "tears", "attachment": "tears" },
	{ "name": "eyes", "bone": "head", "attachment": "eyes" },
	{ "name": "eyebrow", "bone": "brow", "attachment": "eyebrow" }
],
"skins": {
	"default": {
		"body": {
			"body": { "x": 23.94, "y": 223.9, "width": 745, "height": 764 }
		},
		"eyebrow": {
			"eyebrow": { "x": 2.46, "y": -26.28, "width": 159, "height": 32 }
		},
		"eyes": {
			"eyes": { "x": -74.99, "y": 114.95, "width": 155, "height": 97 }
		},
		"face": {
			"face": { "x": -5.99, "y": 164.95, "width": 431, "height": 413 }
		},
		"tears": {
			"tears": { "x": 10.06, "y": -66.95, "width": 199, "height": 113 }
		}
	}
},
"animations": {
	"idle": {
		"bones": {
			"body": {
				"translate": [
					{
						"time": 0,
						"x": 0,
						"y": 0,
						"curve": [ 0.25, 0, 0.75, 1 ]
					},
					{
						"time": 1,
						"x": 0,
						"y": -11.43,
						"curve": [ 0.25, 0, 0.75, 1 ]
					},
					{ "time": 2, "x": 0, "y": 0 }
				]
			},
			"head": {
				"translate": [
					{
						"time": 0,
						"x": 0,
						"y": -1.9,
						"curve": [ 0.25, 0, 0.75, 1 ]
					},
					{
						"time": 0.1666,
						"x": 0,
						"y": 0,
						"curve": [ 0.25, 0, 0.75, 1 ]
					},
					{
						"time": 1.1666,
						"x": 0,
						"y": -11.43,
						"curve": [ 0.25, 0, 0.75, 1 ]
					},
					{ "time": 2, "x": 0, "y": -1.9 }
				]
			},
			"brow": {
				"translate": [
					{
						"time": 0,
						"x": 0,
						"y": -0.63,
						"curve": [ 0.25, 0, 0.75, 1 ]
					},
					{
						"time": 0.1666,
						"x": 0,
						"y": 0,
						"curve": [ 0.25, 0, 0.75, 1 ]
					},
					{
						"time": 1.1666,
						"x": 0,
						"y": -3.81,
						"curve": [ 0.25, 0, 0.75, 1 ]
					},
					{ "time": 2, "x": 0, "y": -0.63 }
				]
			}
		}
	},
	"start": {
		"bones": {
			"body": {
				"translate": [
					{
						"time": 0,
						"x": 0,
						"y": 0,
						"curve": [ 0.25, 0, 0.75, 1 ]
					},
					{
						"time": 0.1666,
						"x": 0,
						"y": -17.15,
						"curve": [ 0.25, 0, 0.75, 1 ]
					},
					{
						"time": 0.3333,
						"x": 0,
						"y": 0,
						"curve": [ 0.25, 0, 0.75, 1 ]
					},
					{
						"time": 0.5,
						"x": 0,
						"y": -17.15,
						"curve": [ 0.25, 0, 0.75, 1 ]
					},
					{
						"time": 0.6666,
						"x": 0,
						"y": 0,
						"curve": [ 0.25, 0, 0.75, 1 ]
					},
					{
						"time": 0.8333,
						"x": 0,
						"y": -17.15,
						"curve": [ 0.25, 0, 0.75, 1 ]
					},
					{ "time": 1, "x": 0, "y": 0 }
				]
			},
			"head": {
				"rotate": [
					{
						"time": 0,
						"angle": 0,
						"curve": [ 0.25, 0, 0.75, 1 ]
					},
					{
						"time": 0.5,
						"angle": 7.8,
						"curve": [ 0.25, 0, 0.75, 1 ]
					},
					{ "time": 1, "angle": 0 }
				],
				"translate": [
					{
						"time": 0,
						"x": 0,
						"y": 0,
						"curve": [ 0.25, 0, 0.75, 1 ]
					},
					{
						"time": 0.5,
						"x": 2.89,
						"y": -21.09,
						"curve": [ 0.25, 0, 0.75, 1 ]
					},
					{ "time": 1, "x": 0, "y": 0 }
				]
			},
			"tears": {
				"scale": [
					{
						"time": 0,
						"x": 1,
						"y": 0,
						"curve": [ 0.25, 0, 0.75, 1 ]
					},
					{ "time": 1, "x": 1, "y": 1 }
				]
			},
			"brow": {
				"translate": [
					{
						"time": 0,
						"x": 0,
						"y": 0,
						"curve": [ 0.25, 0, 0.75, 1 ]
					},
					{ "time": 0.3333, "x": 0, "y": -9.48, "curve": "stepped" },
					{
						"time": 0.6666,
						"x": 0,
						"y": -9.48,
						"curve": [ 0.25, 0, 0.75, 1 ]
					},
					{ "time": 1, "x": 0, "y": 0 }
				]
			}
		}
	}
}
}